datamuse_cli/__init__.py
datamuse_cli/cli.py
datamuser-0.1.1.dist-info/METADATA
datamuser-0.1.1.dist-info/WHEEL
datamuser-0.1.1.dist-info/entry_points.txt
datamuser-0.1.1.dist-info/RECORD
