Metadata-Version: 2.4
Name: datamuser
Version: 0.1.1
Summary: Command line interface for the Datamuse API
Author-email: Hrothgar <hrothgarrrr@gmail.com>
License-Expression: MIT
Keywords: antonyms,cli,datamuse,rhyming,synonyms,thesaurus,words
Requires-Python: >=3.7
Requires-Dist: requests>=2.25.0
